setup.py
kss/__init__.py
kss.templates.egg-info/PKG-INFO
kss.templates.egg-info/SOURCES.txt
kss.templates.egg-info/dependency_links.txt
kss.templates.egg-info/entry_points.txt
kss.templates.egg-info/namespace_packages.txt
kss.templates.egg-info/not-zip-safe
kss.templates.egg-info/requires.txt
kss.templates.egg-info/top_level.txt
kss/templates/__init__.py
kss/templates/util.py
kss/templates/plugin/README.txt_tmpl
kss/templates/plugin/setup.py_tmpl
kss/templates/plugin/+package+/README.txt_tmpl
kss/templates/plugin/+package+/__init__.py_tmpl
kss/templates/plugin/+package+/commands.py_tmpl
kss/templates/plugin/+package+/config.py_tmpl
kss/templates/plugin/+package+/javascript/plugin.js_tmpl
kss/templates/plugin/+package+/tests/__init__.py_tmpl
kss/templates/zope_plugin/setup.py_tmpl
kss/templates/zope_plugin/+package+/README.txt_tmpl
kss/templates/zope_plugin/+package+/commands.py_tmpl
kss/templates/zope_plugin/+package+/config.py_tmpl
kss/templates/zope_plugin/+package+/configure.zcml_tmpl
kss/templates/zope_plugin/+package+/interfaces.py_tmpl
kss/templates/zope_plugin/+package+/demo/__init__.py_tmpl
kss/templates/zope_plugin/+package+/demo/configure.zcml_tmpl
kss/templates/zope_plugin/+package+/demo/demoview.py_tmpl
kss/templates/zope_plugin/+package+/demo/my_demo.kss_tmpl
kss/templates/zope_plugin/+package+/demo/my_demo.pt_tmpl
kss/templates/zope_plugin/+package+/demo/zopeconfig.py_tmpl
kss/templates/zope_plugin/+package+/demo/selenium_tests/README.txt_tmpl
