Metadata-Version: 1.0
Name: kss.templates
Version: 0.1
Summary: Templates for creating KSS plugins
Home-page: http://kssproject.org
Author: KSS Project
Author-email: kss-devel@codespeak.net
License: GPL
Keywords: skeleton kss plugin
Platform: UNKNOWN
Classifier: Development Status :: 3 - Alpha
Classifier: Framework :: Paste
Classifier: Intended Audience :: Developers
Classifier: License :: OSI Approved :: GNU General Public License (GPL)
Classifier: Operating System :: OS Independent
Classifier: Programming Language :: Python
Classifier: Programming Language :: JavaScript
Classifier: Topic :: Software Development :: Code Generators
